rainbowprint/__init__.py
rainbowprint/rainbowprint.py
rainbowprint_TechnoHwizrdry-0.0.5.dist-info/LICENSE
rainbowprint_TechnoHwizrdry-0.0.5.dist-info/METADATA
rainbowprint_TechnoHwizrdry-0.0.5.dist-info/WHEEL
rainbowprint_TechnoHwizrdry-0.0.5.dist-info/top_level.txt
rainbowprint_TechnoHwizrdry-0.0.5.dist-info/RECORD
