Metadata-Version: 2.1
Name: rainbowprint-TechnoHwizrdry
Version: 0.0.5
Summary: Print standard output in colorful gradients.
Home-page: https://github.com/Techno-Hwizrdry/rainbowprint
Author: Techno-Hwizrdry (Alexan Mardigian)
Author-email: <alexan@expresspolygon.com>
Keywords: python,colors,gradient,terminal,output
Classifier: License :: OSI Approved :: MIT License
Classifier: Development Status :: 5 - Production/Stable
Classifier: Intended Audience :: Developers
Classifier: Programming Language :: Python :: 3
Classifier: Programming Language :: Python :: 3 :: Only
Classifier: Programming Language :: Python :: 3.6
Classifier: Programming Language :: Python :: 3.7
Classifier: Programming Language :: Python :: 3.8
Classifier: Programming Language :: Python :: 3.9
Classifier: Programming Language :: Python :: 3.10
Classifier: Topic :: Utilities
Classifier: Operating System :: Unix
Classifier: Operating System :: MacOS :: MacOS X
Classifier: Operating System :: Microsoft :: Windows
Requires-Python: >=3.6
License-File: LICENSE
Requires-Dist: colored ==1.4.3
Requires-Dist: colour ==0.1.5
